badwordfilter/__init__.py
badwordfilter/admin.py
badwordfilter/apps.py
badwordfilter/badwordfilter.py
badwordfilter/cli.py
badwordfilter/models.py
badwordfilter/tests.py
badwordfilter/validators.py
badwordfilter/views.py
badwordfilter/wordlist.txt
badwordfilter-0.1.1.dist-info/AUTHORS.rst
badwordfilter-0.1.1.dist-info/LICENSE
badwordfilter-0.1.1.dist-info/METADATA
badwordfilter-0.1.1.dist-info/WHEEL
badwordfilter-0.1.1.dist-info/entry_points.txt
badwordfilter-0.1.1.dist-info/top_level.txt
badwordfilter-0.1.1.dist-info/RECORD
