Metadata-Version: 2.1
Name: badwordfilter
Version: 0.1.1
Summary: 敏感词过滤器, bad word filter
Home-page: https://github.com/riiy/badwordfilter
Author: riiy
Author-email: congminghaoxue@gmail.com
License: MIT license
Keywords: badwordfilter
Platform: UNKNOWN
Classifier: Environment :: Web Environment
Classifier: Framework :: Django
Classifier: Framework :: Django :: 2.0
Classifier: Intended Audience :: Developers
Classifier: License :: OSI Approved :: MIT License
Classifier: Operating System :: OS Independent
Classifier: Programming Language :: Python
Classifier: Programming Language :: Python :: 3.5
Classifier: Programming Language :: Python :: 3.6
Classifier: Topic :: Internet :: WWW/HTTP
Classifier: Topic :: Internet :: WWW/HTTP :: Dynamic Content
Requires-Dist: Click (>=6.0)
Requires-Dist: inflection
